natLight/__init__.py
natLight/natLight.py
natLight-0.3.dist-info/LICENSE
natLight-0.3.dist-info/METADATA
natLight-0.3.dist-info/WHEEL
natLight-0.3.dist-info/top_level.txt
natLight-0.3.dist-info/RECORD
