Metadata-Version: 2.1
Name: natLight
Version: 0.3
Summary: Natural Ligth to RGB Converter
Home-page: https://gitlab.com/stroblme/naturalLight.git
Author: Melvin Strobl
License: UNKNOWN
Platform: UNKNOWN
Requires-Python: >=3.6
